fastapi_cruddy_framework/__init__.py
fastapi_cruddy_framework/adapters.py
fastapi_cruddy_framework/cli/__init__.py
fastapi_cruddy_framework/cli/generators.py
fastapi_cruddy_framework/cli/main.py
fastapi_cruddy_framework/cli/templates.py
fastapi_cruddy_framework/controller.py
fastapi_cruddy_framework/exceptions.py
fastapi_cruddy_framework/graphql.py
fastapi_cruddy_framework/inflector.py
fastapi_cruddy_framework/pubsub.py
fastapi_cruddy_framework/repository.py
fastapi_cruddy_framework/resource.py
fastapi_cruddy_framework/router.py
fastapi_cruddy_framework/schemas.py
fastapi_cruddy_framework/security.py
fastapi_cruddy_framework/test_helpers.py
fastapi_cruddy_framework/util.py
fastapi_cruddy_framework/websocket_manager.py
fastapi_cruddy_framework-1.12.1.dist-info/LICENSE
fastapi_cruddy_framework-1.12.1.dist-info/METADATA
fastapi_cruddy_framework-1.12.1.dist-info/WHEEL
fastapi_cruddy_framework-1.12.1.dist-info/entry_points.txt
fastapi_cruddy_framework-1.12.1.dist-info/RECORD
