Metadata-Version: 2.3
Name: fastapi-cruddy-framework
Version: 1.12.1
Summary: A holistic CRUD/MVC framework for FastAPI, with endpoint policies and relationships
Keywords: fastapi,crud,mvc,orm,ember,sails,json
Author: mdconaway
Author-email: mdconaway@users.noreply.github.com
Requires-Python: >=3.10,<4.0
Classifier: Development Status :: 5 - Production/Stable
Classifier: Environment :: Web Environment
Classifier: Framework :: FastAPI
Classifier: Operating System :: OS Independent
Classifier: Programming Language :: Python :: 3
Classifier: Programming Language :: Python :: 3.10
Classifier: Programming Language :: Python :: 3.11
Classifier: Programming Language :: Python :: 3.12
Classifier: Programming Language :: Python :: 3.13
Classifier: Topic :: Software Development
Classifier: Topic :: Software Development :: Libraries :: Application Frameworks
Classifier: Topic :: Software Development :: Libraries :: Python Modules
Requires-Dist: SQLAlchemy-Utils (>=0.42.1,<0.43.0)
Requires-Dist: SQLAlchemy[asyncio] (>=2.0.0)
Requires-Dist: async-asgi-testclient (>=1.4.11,<2.0.0)
Requires-Dist: async-timeout (>=5.0.1)
Requires-Dist: click (>=8.1.0,<9.0.0)
Requires-Dist: fakeredis (>=2.33.0)
Requires-Dist: fastapi[all] (>=0.128.0)
Requires-Dist: inflect (>=7.0.0,<8.0.0)
Requires-Dist: pydantic-settings (>=2.0.0)
Requires-Dist: pymitter (>=1.1.3)
Requires-Dist: redis (>=7.1.0)
Requires-Dist: sqlmodel (>=0.0.31,<0.0.32)
Requires-Dist: strawberry-graphql[fastapi] (>=0.289.8)
Requires-Dist: uuid7 (>=0.1.0,<0.2.0)
Requires-Dist: validator-collection (>=1.5.0,<2.0.0)
Project-URL: Homepage, https://github.com/mdconaway/fastapi-cruddy-framework
Project-URL: Repository, https://github.com/mdconaway/fastapi-cruddy-framework
